{
  "id": "MAP_LAVERIA_CITY",
  "name": "LaveriaCity",
  "layout": "LAYOUT_LAVERIA_CITY",
  "music": "MUS_B_ARENA",
  "region_map_section": "MAPSEC_LAVERIA_CITY",
  "requires_flash": false,
  "weather": "WEATHER_NONE",
  "map_type": "MAP_TYPE_CITY",
  "allow_cycling": true,
  "allow_escaping": false,
  "allow_running": true,
  "show_map_name": true,
  "battle_scene": "MAP_BATTLE_SCENE_NORMAL",
  "connections": 0,
  "object_events": [

  ],
  "warp_events": [
    {
      "x": 25,
      "y": 40,
      "elevation": 0,
      "dest_map": "MAP_LAVERIA_CITY_POKEMON_CENTER_1F",
      "dest_warp_id": 0
    },
    {
      "x": 55,
      "y": 39,
      "elevation": 0,
      "dest_map": "MAP_STEEP_RAVINE",
      "dest_warp_id": 0
    },
    {
      "x": 11,
      "y": 39,
      "elevation": 0,
      "dest_map": "MAP_LAVERIA_CITY_HOUSE1",
      "dest_warp_id": 0
    },
    {
      "x": 32,
      "y": 27,
      "elevation": 0,
      "dest_map": "MAP_LAVERIA_CITY_HOUSE2",
      "dest_warp_id": 0
    },
    {
      "x": 15,
      "y": 31,
      "elevation": 0,
      "dest_map": "MAP_LAVERIA_CITY_MART",
      "dest_warp_id": 0
    },
    {
      "x": 29,
      "y": 49,
      "elevation": 0,
      "dest_map": "MAP_LAVERIA_CITY_INTERLINK",
      "dest_warp_id": 0
    },
    {
      "x": 30,
      "y": 49,
      "elevation": 0,
      "dest_map": "MAP_LAVERIA_CITY_INTERLINK",
      "dest_warp_id": 0
    },
    {
      "x": 7,
      "y": 24,
      "elevation": 0,
      "dest_map": "MAP_LAVERIA_CITY_INTERLINK",
      "dest_warp_id": 0
    },
    {
      "x": 7,
      "y": 25,
      "elevation": 0,
      "dest_map": "MAP_LAVERIA_CITY_INTERLINK",
      "dest_warp_id": 0
    },
    {
      "x": 7,
      "y": 26,
      "elevation": 0,
      "dest_map": "MAP_LAVERIA_CITY_INTERLINK",
      "dest_warp_id": 0
    }
  ],
  "coord_events": [

  ],
  "bg_events": [

  ]
}
